{
    "cordova-plugin-whitelist": {
        "source": {
            "type": "registry",
            "id": "cordova-plugin-whitelist@~1.2.0"
        },
        "is_top_level": true,
        "variables": {}
    },
    "cordova-plugin-console": {
        "source": {
            "type": "registry",
            "id": "cordova-plugin-console@~1.0.1"
        },
        "is_top_level": true,
        "variables": {}
    },
    "cordova-plugin-statusbar": {
        "source": {
            "type": "registry",
            "id": "cordova-plugin-statusbar@~1.0.1"
        },
        "is_top_level": true,
        "variables": {}
    },
    "cordova-plugin-geolocation": {
        "source": {
            "type": "registry",
            "id": "cordova-plugin-geolocation"
        },
        "is_top_level": true,
        "variables": {}
    },
    "cordova-plugin-compat": {
        "source": {
            "type": "registry",
            "id": "cordova-plugin-compat@^1.0.0"
        },
        "is_top_level": false,
        "variables": {}
    },
    "org.apache.cordova.media": {
        "source": {
            "type": "registry",
            "id": "cordova-plugin-media@0.2.8"
        },
        "is_top_level": true,
        "variables": {}
    },
    "cordova.plugins.diagnostic": {
        "source": {
            "type": "registry",
            "id": "cordova.plugins.diagnostic@~3.6.8"
        },
        "is_top_level": true,
        "variables": {}
    }
}